<?xml version="1.0" encoding="utf-8"?>
<TextureAtlas imagePath="logoBumpinSpooky.png">
	<!-- Created with Adobe Animate version 21.0.5.40714 -->
	<!-- http://www.adobe.com/products/animate.html -->
	<SubTexture name="logo bumpin0000" x="0" y="0" width="937" height="623" pivotX="6.75" pivotY="-69.1" frameX="-21" frameY="-13" frameWidth="984" frameHeight="654"/>
	<SubTexture name="logo bumpin0001" x="937" y="0" width="984" height="654"/>
	<SubTexture name="logo bumpin0002" x="937" y="0" width="984" height="654"/>
	<SubTexture name="logo bumpin0003" x="0" y="654" width="956" height="636" frameX="-12" frameY="-7" frameWidth="984" frameHeight="654"/>
	<SubTexture name="logo bumpin0004" x="0" y="654" width="956" height="636" frameX="-12" frameY="-7" frameWidth="984" frameHeight="654"/>
	<SubTexture name="logo bumpin0005" x="956" y="654" width="948" height="630" frameX="-16" frameY="-10" frameWidth="984" frameHeight="654"/>
	<SubTexture name="logo bumpin0006" x="956" y="654" width="948" height="630" frameX="-16" frameY="-10" frameWidth="984" frameHeight="654"/>
	<SubTexture name="logo bumpin0007" x="956" y="654" width="948" height="630" frameX="-16" frameY="-10" frameWidth="984" frameHeight="654"/>
	<SubTexture name="logo bumpin0008" x="956" y="654" width="948" height="630" frameX="-16" frameY="-10" frameWidth="984" frameHeight="654"/>
	<SubTexture name="logo bumpin0009" x="956" y="654" width="948" height="630" frameX="-16" frameY="-10" frameWidth="984" frameHeight="654"/>
	<SubTexture name="logo bumpin0010" x="956" y="654" width="948" height="630" frameX="-16" frameY="-10" frameWidth="984" frameHeight="654"/>
	<SubTexture name="logo bumpin0011" x="956" y="654" width="948" height="630" frameX="-16" frameY="-10" frameWidth="984" frameHeight="654"/>
	<SubTexture name="logo bumpin0012" x="956" y="654" width="948" height="630" frameX="-16" frameY="-10" frameWidth="984" frameHeight="654"/>
	<SubTexture name="logo bumpin0013" x="956" y="654" width="948" height="630" frameX="-16" frameY="-10" frameWidth="984" frameHeight="654"/>
	<SubTexture name="logo bumpin0014" x="956" y="654" width="948" height="630" frameX="-16" frameY="-10" frameWidth="984" frameHeight="654"/>
</TextureAtlas>
